giraffe/__init__.py
giraffe/callback.py
giraffe/crossover.py
giraffe/draw.py
giraffe/fitness.py
giraffe/functions.py
giraffe/giraffe.py
giraffe/globals.py
giraffe/lib_types.py
giraffe/mutation.py
giraffe/node.py
giraffe/operators.py
giraffe/pareto.py
giraffe/population.py
giraffe/tree.py
giraffe/utils.py
giraffe/backend/__init__.py
giraffe/backend/backend.py
giraffe/backend/backend_interface.py
giraffe/backend/numpy_backend.py
giraffe/backend/pytorch.py
giraffe_genetic-0.1.0.dist-info/licenses/LICENSE
giraffe_genetic-0.1.0.dist-info/METADATA
giraffe_genetic-0.1.0.dist-info/WHEEL
giraffe_genetic-0.1.0.dist-info/top_level.txt
giraffe_genetic-0.1.0.dist-info/RECORD
