Metadata-Version: 2.4
Name: giraffe-genetic
Version: 0.1.0
Summary: Giraffe is a genetic programming based algorithm for ensemble creation.
Requires-Python: >=3.12
License-File: LICENSE
Requires-Dist: graphviz>=0.20.3
Requires-Dist: numpy>=2.2.1
Requires-Dist: loguru>=0.7.3
Requires-Dist: scikit-learn>=1.6.1
Requires-Dist: pre-commit>=4.2.0
Requires-Dist: matplotlib>=3.10.1
Dynamic: license-file
